eiffel2/__init__.py
eiffel2-0.0.4.dist-info/LICENSE
eiffel2-0.0.4.dist-info/METADATA
eiffel2-0.0.4.dist-info/WHEEL
eiffel2-0.0.4.dist-info/top_level.txt
eiffel2-0.0.4.dist-info/RECORD
