Metadata-Version: 2.1
Name: eiffel2
Version: 0.0.4
Summary: Neural Network visualization tool
Home-page: https://github.com/Ale9806/Eiffel2
Author: Eduardo Alejandro Lozano Garcia
Author-email: sagrario3098@gmail.com
License: UNKNOWN
Platform: UNKNOWN
Classifier: Programming Language :: Python :: 3
Classifier: License :: OSI Approved :: MIT License
Classifier: Operating System :: OS Independent
Requires-Python: >=3.6
